cyandrocel/LICENSE
cyandrocel/README.md
cyandrocel/__init__.py
cyandrocel/cppsleep.hpp
cyandrocel/errorwriter.py
cyandrocel/fuzzmatcher.h
cyandrocel/logo.png
cyandrocel/nonblockingsubprocess.hpp
cyandrocel/requirements.txt
cyandrocel/split_string.hpp
cyandrocel/stripstring.hpp
cyandrocel/thirdparty.json
cyandrocel/timeoutstuff.hpp
cyandrocel/uiev.pyx
cyandrocel/uiev_compile.py
cyandrocel-1.1.6.dist-info/LICENSE.rst
cyandrocel-1.1.6.dist-info/METADATA
cyandrocel-1.1.6.dist-info/WHEEL
cyandrocel-1.1.6.dist-info/top_level.txt
cyandrocel-1.1.6.dist-info/RECORD
