Metadata-Version: 2.2
Name: cyandrocel
Version: 1.1.6
Summary: Android Automation Framework for real devices without root access
Home-page: https://github.com/hansalemaos/cyandrocel
Author: Johannes Fischer
Author-email: aulasparticularesdealemaosp@gmail.com
License: MIT
Keywords: Android,Automation,Cython,Pandas,Adb,Numpy
Classifier: Development Status :: 4 - Beta
Classifier: Programming Language :: Python :: 3 :: Only
Classifier: Programming Language :: Python :: 3.10
Classifier: Topic :: Software Development :: Libraries :: Python Modules
Classifier: Topic :: Utilities
License-File: LICENSE.rst
Requires-Dist: Cython
Requires-Dist: numpy
Requires-Dist: pandas
Requires-Dist: regex
Requires-Dist: requests
Requires-Dist: setuptools
Requires-Dist: ziglang
Dynamic: author
Dynamic: author-email
Dynamic: classifier
Dynamic: description
Dynamic: description-content-type
Dynamic: home-page
Dynamic: keywords
Dynamic: license
Dynamic: requires-dist
Dynamic: summary
